{
  "Source": "Credere_mail_test <credereadmin@open-contracting.org>",
  "Template": "credere-ConfirmEmailChange",
  "Destination": {
    "ToAddresses": [
      "credereadmin@open-contracting.org"
    ]
  },
  "TemplateData": "{\"NEW_MAIL\": \"test@mail.com\", \"AWARD_SUPPLIER_NAME\": \"PROVEEDOR XX\", \"CONFIRM_EMAIL_CHANGE_URL\": \"www.google.com\", \"CONFIRM_EMAIL_CHANGE_IMAGE_LINK\": \"http://ocp22.open-contracting.org/images/confirmemailchange.png\", \"LINK-TO-WEB-VERSION\": \"www.google.com\", \"OCP_LOGO\": \"http://ocp22.open-contracting.org/images/logoocp.jpg\", \"TWITTER_LOGO\": \"http://ocp22.open-contracting.org/images/twiterlogo.png\", \"FB_LOGO\": \"http://ocp22.open-contracting.org/images/facebook.png\", \"LINK_LOGO\": \"http://ocp22.open-contracting.org/images/link.png\", \"TWITTER_LINK\": \"www.google.com\", \"FACEBOOK_LINK\": \"www.google.com\", \"LINK_LINK\": \"www.google.com\"}"
}
